{
  "${ModID}:ConfigMenuText": {
    "TEXT": [
      "生态尖塔",
      "StS Modding Community",
      "让尖塔地图变得更加有趣",
      "开启",
      "让地图中的群落图标变得更大，但过大的图标可能会显示不全",
      "在一个生态群落中只会触发一次群落事件，取消勾选则会多次触发",
      "开启着色器"
    ]
  },
  "${ModID}:SingleCardReward": {
    "TEXT": [
      "[卡牌] ",
      "提示：右击查看详细卡牌信息！"
    ]
  },
  "${ModID}:HealReward": {
    "TEXT": [
      "回复 "
    ]
  },
  "${ModID}:AnyColorCardReward": {
    "TEXT": [
      "添加一张任意颜色的卡牌",
      "选择一张卡牌"
    ]
  },
  "${ModID}:CombatExplainButton": {
    "TEXT": [
      "生态群落"
    ]
  },
  "${ModID}:RunHistoryScreen": {
    "TEXT": [
      "生态群落: {0}"
    ]
  },
  "${ModID}:ZonePotionsPatch": {
    "TEXT": [
      "生态群落：",
      "只能在特定生态群落中获得的药水。"
    ]
  },
  "${ModID}:CharacterSelectScreen": {
    "TEXT": [
      "开启生态群落",
      "为尖塔添加各种生态群落，让地图拥有更加生动、有趣"
    ]
  },
  "${ModID}:ZoneTooltip": {
    "TEXT": [
      "#p作者: {0}"
    ]
  }
}
