{
	"monsters": [
		{
			"name": "Shield Gremlin (Bodyguard)",
			"id": "${ModID}:GremlindBodyGuard",
			"ai": [
				{
					"min_asc": 0,
					"desc": "#wProtects random allies (except other Shield Gremlins) until none remain, and then uses #wShield #wBash.",
					"hp": "(18 - 21 HP)",
					"notes": "",
					"moves": [
						{
							"name": "Protect",
							"effects": [
								{
									"name": "Ally Block 7",
									"color": "BLOCK"
								}
							]
						},
						{
							"name": "Shield Bash",
							"effects": [
								{
									"name": "6",
									"color": "DAMAGE"
								},
								{
									"name": "Strength 5",
									"color": "BUFF"
								}
							]
						}
					]
				},
				{
					"min_asc": 2,
					"desc": "#wProtects random allies (except other Shield Gremlins) until none remain, and then uses #wShield #wBash.",
					"hp": "(18 - 21 HP)",
					"notes": "",
					"moves": [
						{
							"name": "Protect",
							"effects": [
								{
									"name": "Ally Block 7",
									"color": "BLOCK"
								}
							]
						},
						{
							"name": "Shield Bash",
							"effects": [
								{
									"name": "8",
									"color": "DAMAGE"
								},
								{
									"name": "Strength 5",
									"color": "BUFF"
								}
							]
						}
					]
				},
				{
					"min_asc": 7,
					"desc": "#wProtects random allies (except other Shield Gremlins) until none remain, and then uses #wShield #wBash.",
					"hp": "(19 - 23 HP)",
					"notes": "",
					"moves": [
						{
							"name": "Protect",
							"effects": [
								{
									"name": "Ally Block 8",
									"color": "BLOCK"
								}
							]
						},
						{
							"name": "Shield Bash",
							"effects": [
								{
									"name": "8",
									"color": "DAMAGE"
								},
								{
									"name": "Strength 5",
									"color": "BUFF"
								}
							]
						}
					]
				},
				{
					"min_asc": 17,
					"desc": "#wProtects random allies (except other Shield Gremlins) until none remain, and then uses #wShield #wBash.",
					"hp": "(19 - 23 HP)",
					"notes": "",
					"moves": [
						{
							"name": "Protect",
							"effects": [
								{
									"name": "Ally Block 11",
									"color": "BLOCK"
								}
							]
						},
						{
							"name": "Shield Bash",
							"effects": [
								{
									"name": "8",
									"color": "DAMAGE"
								},
								{
									"name": "Strength 5",
									"color": "BUFF"
								}
							]
						}
					]
				}
			]
		},
		{
			"name": "Feral Gremlin",
			"id": "${ModID}:GremlinDog",
			"ai": [
				{
					"min_asc": 0,
					"desc": "Starts with #wPoison #wFang or #wDefensive #wNibble (using a different move from other Feral Gremlins if possible) and then alternates between the two moves.",
					"hp": "(21 - 27 HP)",
					"notes": "",
					"moves": [
						{
							"name": "Poison Fang",
							"effects": [
								{
									"name": "4",
									"color": "DAMAGE"
								},
								{
									"name": "Poison 4",
									"color": "DEBUFF"
								}
							]
						},
						{
							"name": "Defensive Nibble",
							"effects": [
								{
									"name": "8",
									"color": "DAMAGE"
								},
								{
									"name": "6",
									"color": "BLOCK"
								}
							]
						}
					]
				},
				{
					"min_asc": 2,
					"desc": "Starts with #wPoison #wFang or #wDefensive #wNibble (using a different move from other Feral Gremlins if possible) and then alternates between the two moves.",
					"hp": "(21 - 27 HP)",
					"notes": "",
					"moves": [
						{
							"name": "Poison Fang",
							"effects": [
								{
									"name": "4",
									"color": "DAMAGE"
								},
								{
									"name": "Poison 4",
									"color": "DEBUFF"
								}
							]
						},
						{
							"name": "Defensive Nibble",
							"effects": [
								{
									"name": "9",
									"color": "DAMAGE"
								},
								{
									"name": "6",
									"color": "BLOCK"
								}
							]
						}
					]
				},
				{
					"min_asc": 7,
					"desc": "Starts with #wPoison #wFang or #wDefensive #wNibble (using a different move from other Feral Gremlins if possible) and then alternates between the two moves.",
					"hp": "(23 - 29 HP)",
					"notes": "",
					"moves": [
						{
							"name": "Poison Fang",
							"effects": [
								{
									"name": "4",
									"color": "DAMAGE"
								},
								{
									"name": "Poison 4",
									"color": "DEBUFF"
								}
							]
						},
						{
							"name": "Defensive Nibble",
							"effects": [
								{
									"name": "9",
									"color": "DAMAGE"
								},
								{
									"name": "6",
									"color": "BLOCK"
								}
							]
						}
					]
				},
				{
					"min_asc": 17,
					"desc": "Starts with #wPoison #wFang or #wDefensive #wNibble (using a different move from other Feral Gremlins if possible) and then alternates between the two moves.",
					"hp": "(23 - 29 HP)",
					"notes": "",
					"moves": [
						{
							"name": "Poison Fang",
							"effects": [
								{
									"name": "4",
									"color": "DAMAGE"
								},
								{
									"name": "Poison 6",
									"color": "DEBUFF"
								}
							]
						},
						{
							"name": "Defensive Nibble",
							"effects": [
								{
									"name": "9",
									"color": "DAMAGE"
								},
								{
									"name": "9",
									"color": "BLOCK"
								}
							]
						}
					]
				}
			]
		}
	]
}