{
  "${ModID}:DivinitiesGaze": {
    "TEXT": [
      "神之凝视",
      "诸神降临！你能引起他们的关注吗？能赢得他们的青睐吗？ NL NL 战斗开始时，从随机神灵中获取一张 #g强力卡牌 和一些 #r状态 牌。",
      "Shammy, NoelleDevo, PitohuiArt"
    ]
  },
  "${ModID}:DivinitiesGaze_Divinity_Eclectic": {
    "TEXT": [
      "通过知识取得进步。",
      "通过进步获取知识。",
      "你以前见到过...",
      "再次，他们攀登..."
    ],
    "TEXT_DICT": {
      "NAME": "帕拉斯",
      "TITLE": "智慧之神",
      "EVENT_TEXT": "翻书的声音与大部头书籍的陈旧味道萦绕着你。你们眼神碰到了一起 NL NL 在他们眼中，你看到了 #r过去 ，也见到了 #g未来 NL NL 他们说到: \"又一个... #y@求知者@ ...\"",
      "EVENT_BUTTON_TEXT": "[学习] #g从5张已升级的卡牌中选择1张加入你的牌组",
      "EVENT_ACCEPT_TEXT": "~安静...~ NL NL 如同深夜的图书馆一样，他们离开时没有任何声音。你学到了 #g知识... 但你所看到的一切很难忘记",
      "EVENT_REJECT_TEXT": "~安静...~ NL NL 如同深夜的图书馆一样，他们离开时没有任何声音。他们能教你什么呢？你认真听了吗? NL NL 你做出了正确的选择吗？",
      "SELECT_TEXT": "选择一张牌加入你的牌组"
    }
  },
  "${ModID}:DivinitiesGaze_Divinity_End": {
    "TEXT": [
      "..."
    ],
    "TEXT_DICT": {
      "NAME": "虚空",
      "TITLE": "终焉之神",
      "EVENT_TEXT": "你周围的世界坠入了黑暗，连同你的思绪也被拖入了深渊。深渊 ~吞噬~ 了你的躯体与灵魂，直到你失去了曾经的一切 NL NL 你看到了他们。他们是谁？你似乎知道，但却怎么也想不起来。这就是 #r虚空 吗? NL NL ~仿佛片刻，又似万年~ ，转瞬之间一切便 #r@消失@ 了",
      "EVENT_BUTTON_TEXT": "[遗忘] #g从牌组中选择1张牌并移除。",
      "EVENT_ACCEPT_TEXT": "你的眼睛与思绪重新捕捉到了光芒... 但似乎... 还有点暗？你为什么出现在这里？ NL NL 此刻的你 #y@孜然一身@ NL NL 你感觉内心充斥着 #r@空虚@ ",
      "EVENT_REJECT_TEXT": "你的眼睛与思绪重新捕捉到了光芒... 甚至还有些刺眼。虚空在你内心飘荡，但它并不会吞噬你。",
      "EVENT_BUTTON_UNAVAILABLE_TEXT": "[锁定] 需要你的牌组中至少有1张牌。",
      "SELECT_TEXT": "选择一张牌从你的牌组中移除"
    }
  },
  "${ModID}:DivinitiesGaze_Divinity_Jurors": {
    "TEXT": [
      "你在接受审判。",
      "以正义之名！",
      "判他们有罪。"
    ],
    "TEXT_DICT": {
      "NAME": "阿努比斯",
      "TITLE": "审判之神",
      "EVENT_TEXT": "~开庭~ 你被密密麻麻的身影包围着，任由他们摆布 NL NL \"有罪！有罪！ #r@有罪！\",@ 一个声音在哭泣。 NL NL \"你审判地 #g~太草率~ 了...\", 声音回荡... NL NL \"也许，对于  #y罪犯 ，要以牙还牙？\"... 他们转头目光聚集在你身上， 你的 #r~审判~ 即将到来",
      "EVENT_BUTTON_TEXT": "[审判] 进入精英战斗。 #y对所有人施加3层判决。",
      "EVENT_ACCEPT_TEXT": "审判结束了，天平已然倾斜。陪审员们拖着脚步走出法庭。你的罪名已确立，该赎罪了 NL NL 世界的 #r谬误 需要由你 #g纠正",
      "EVENT_REJECT_TEXT": "审判结束了，天平已然倾斜。陪审员们拖着脚步走出法庭。没有任何定罪。 NL NL 你是 #g清白 的？还是 #r骗了他们？也许你耍了他们 NL NL ... NL NL 也许他们知道"
    }
  },
  "${ModID}:DivinitiesGaze_Divinity_Primordial": {
    "TEXT": [
      "...",
      "生长...",
      "延展...",
      "分裂...",
      "吞噬..."
    ],
    "TEXT_DICT": {
      "NAME": "史莱姆",
      "TITLE": "分裂之神",
      "EVENT_TEXT": "你迈了一步，脚陷入了一滩史莱姆黏液之中。你 #r~动弹不得~ NL NL 你每眨一次眼，它都会成倍地增长，迅速蔓延到你的身体上，它堵塞住了你的嘴巴... 你的鼻子 ...你的耳朵... 你的 @眼睛...@ NL NL 你感觉 #r~如同死亡将至~ 尽管你的肺部被堵住了，但似乎它们在用它们自己的语言 ~说着话~ #g@\"分裂...\"@",
      "EVENT_BUTTON_TEXT": "[分裂] #g复制你牌组中的一张卡牌，并随机再复制另一张卡牌。",
      "EVENT_BUTTON_UNAVAILABLE_TEXT": "[锁定] 需要你的牌组中至少有1张牌。",
      "EVENT_ACCEPT_TEXT": "你的身体又属于你自己了。你不再任由史莱姆吞噬了。 但感觉你已不再是你，仿佛由无数存在组成的 NL NL 你们将一起 #g生长，必须如此",
      "EVENT_REJECT_TEXT": "你的身体又属于你自己了。你不再任由史莱姆吞噬了。 你是独一无二的 NL NL 但似乎又感觉有一丝... #r@孤寂@",
      "SELECT_TEXT": "选择一张牌来复制"
    }
  },
  "${ModID}:DivinitiesGaze_Divinity_Torch": {
    "TEXT": [
      "我与你同在！",
      "黑暗中的光",
      "一丝希望..."
    ],
    "TEXT_DICT": {
      "NAME": "赫菲斯托斯",
      "TITLE": "火焰之神",
      "EVENT_TEXT": "#r~烈焰~ 吞噬！ 转瞬之间你的身躯就要 #r烧焦 。然而，似乎一点也不痛...甚至感到些许温暖...舒适... NL NL \"孩子，尖塔是属于你的。去探索，去 #g成长 吧，我们会指引你的\"",
      "EVENT_BUTTON_TEXT": "[浴火] #g回复%d生命值。 #g升级你牌组中的1张随机卡牌",
      "EVENT_BUTTON_UNAVAILABLE_TEXT": "[锁定] 需要未满的生命值或可升级的卡牌。",
      "EVENT_ACCEPT_TEXT": "灼热的火焰逐渐变成微弱的暖光。你走的道路愈加 #g明亮 NL NL 你并不知道他究竟是谁，但你感觉到了背后的他是你的朋友",
      "EVENT_REJECT_TEXT": "灼热的火焰逐渐变成微弱的暖光。你走的道路愈加 #r黑暗 NL NL 也许，如果当初你选择了接受，事情可能会有所不同？"
    }
  }
}